[[0,["start",{"id":1658272079812,"collapsed":false,"xcor":0,"ycor":0,"heading":0,"color":10,"shade":60,"pensize":5,"grey":92.85714285714286}],434,-46,[null,1,null]],[1,"settimbre",448,-5,[0,2,53,3]],[2,["voicename",{"value":"violin"}],599,-5,[1]],[3,"hidden",448,436,[1,4]],[4,["newnote",{"collapsed":false}],448,436,[3,5,8,12]],[5,"divide",550,436,[4,6,7]],[6,["number",{"value":2}],636,436,[5]],[7,["number",{"value":4}],636,468,[5]],[8,"vspace",462,468,[4,9]],[9,"pitch",462,500,[8,10,11,null]],[10,["solfege",{"value":"sol"}],536,500,[9]],[11,["number",{"value":4}],536,532,[9]],[12,"hidden",448,594,[4,31]],[13,["newnote",{"collapsed":false}],476,59,[53,14,17,21]],[14,"divide",578,59,[13,15,16]],[15,["number",{"value":1}],664,59,[14]],[16,["number",{"value":4}],664,91,[14]],[17,"vspace",490,91,[13,18]],[18,"pitch",490,123,[17,19,20,null]],[19,["solfege",{"value":"mi"}],564,123,[18]],[20,["number",{"value":4}],564,155,[18]],[21,"hidden",476,217,[13,22]],[22,["newnote",{"collapsed":false}],476,217,[21,23,26,30]],[23,"divide",578,217,[22,24,25]],[24,["number",{"value":1}],664,217,[23]],[25,["number",{"value":2}],664,249,[23]],[26,"vspace",490,249,[22,27]],[27,"pitch",490,281,[26,28,29,null]],[28,["solfege",{"value":"sol"}],564,281,[27]],[29,["number",{"value":4}],564,313,[27]],[30,"hidden",476,375,[22,null]],[31,"setdrum",448,594,[12,32,33,38]],[32,["drumname",{"value":"japanese drum"}],563,594,[31]],[33,"rhythm2",462,626,[31,34,35,45]],[34,["number",{"value":1}],551,626,[33]],[35,"divide",551,658,[33,36,37]],[36,["number",{"value":2}],637,658,[35]],[37,["number",{"value":1}],637,690,[35]],[38,"hidden",448,1004,[31,null]],[39,"pitch",462,721,[45,40,41,46]],[40,["solfege",{"value":"sol"}],536,721,[39]],[41,["number",{"value":2}],536,753,[39]],[42,"pitch",462,911,[51,43,44,null]],[43,["solfege",{"value":"do"}],536,911,[42]],[44,["number",{"value":2}],536,943,[42]],[45,"vspace",462,689,[33,39]],[46,"setbpm3",462,784,[39,47,48,55]],[47,["number",{"value":90}],602,784,[46]],[48,"divide",602,816,[46,49,50]],[49,["number",{"value":1}],688,816,[48]],[50,["number",{"value":4}],688,848,[48]],[51,"vspace",462,879,[55,42]],[52,["drumname",{"value":"kick drum"}],552,1377,[null]],[53,"repeat",462,27,[1,54,13,null]],[54,["number",{"value":4}],564,27,[53]],[55,"playdrum",462,847,[46,56,51]],[56,["effectsname",{"value":"duck"}],536,847,[55]]]